yapic/__init__.py
yapic/deepimagej_exporter.py
yapic/main.py
yapic/network.py
yapic/session.py
yapic/utils.py
yapic/version.py
yapic/networks/__init__.py
yapic/networks/convnet_for_unittest.py
yapic/networks/unet_2d.py
yapic/networks/unet_multi_z.py
yapic/templates/deepimagej101/config.xml
yapic/templates/deepimagej101/postprocessing.txt
yapic/templates/deepimagej101/preprocessing.txt
yapic/tests/__init__.py
yapic/tests/test_exporter.py
yapic/tests/test_network.py
yapic/tests/test_session.py
yapic-1.3.1.dist-info/LICENSE
yapic-1.3.1.dist-info/METADATA
yapic-1.3.1.dist-info/WHEEL
yapic-1.3.1.dist-info/entry_points.txt
yapic-1.3.1.dist-info/top_level.txt
yapic-1.3.1.dist-info/RECORD
