Metadata-Version: 2.1
Name: yapic
Version: 1.3.1
Summary: Yet another Pixel Classifier (based on deep learning)
Home-page: https://yapic.github.io/yapic/
Author: Manuel Schoelling, Christoph Moehl
Author-email: manuel.schoelling@gmx.de, christoph.oliver.moehl@gmail.com
License: UNKNOWN
Platform: UNKNOWN
License-File: LICENSE
Requires-Dist: yapic-io (>=0.2.6)
Requires-Dist: docopt (>=0.6.2)
Requires-Dist: numpy (>=1.15.4)
